09_ALU/adder.v

module adder (A, B, Cin, S, Cout);

input  A, B, Cin;
output S, Cout;

`ifdef DATAFLOW_LEVEL1
assign S    = A ^ B ^ Cin;
assign Cout = (A & B) | (A & Cin) | (B & Cin); 

`elsif GATE_LEVEL
xor x0(S, A, B, Cin);

wire w0, w1, w2;
and a0(w0, A, B);
and a1(w1, A, Cin);
and a2(w2, B, Cin);

or o0(Cout, w0, w1, w2);

`endif

endmodule

07_adder/adder_test.v
`timescale 1ns/1ps

module adder_test(t1, t2, t3, p1, p2);

output t1, t2, t3;
input  p1, p2;

reg t1, t2, t3;

initial begin
    t1 <= 1'b0; t2 <= 1'b0; t3 <= 1'b0;

    #100;
    t1 <= 1'b0; t2 <= 1'b0; t3 <= 1'b1;

    #100;
    t1 <= 1'b0; t2 <= 1'b1; t3 <= 1'b0;

    #100;
    t1 <= 1'b0; t2 <= 1'b1; t3 <= 1'b1;

    #100;
    t1 <= 1'b1; t2 <= 1'b0; t3 <= 1'b0;

    #100;
    t1 <= 1'b1; t2 <= 1'b0; t3 <= 1'b1;

    #100;
    t1 <= 1'b1; t2 <= 1'b1; t3 <= 1'b0;

    #100;
    t1 <= 1'b1; t2 <= 1'b1; t3 <= 1'b1;

    #100;
    $finish;
end

endmodule

07_adder/tb_testbench.v
`timescale 1ns/1ps

//`define DATAFLOW_LEVEL1
`define GATE_LEVEL

module tb_testbench;

wire A, B, CIN, S, COUT;

adder_test tester(.t1(CIN), .t2(A), .t3(B), .p1(S), .p2(COUT));
//                    |       |        |      ▲         ▲
//                    ▼       ▼        ▼      |         |
adder       dut  (.Cin(CIN), .A(A), .B(B), .S(S), .Cout(COUT));

always @(A or B or CIN or S or COUT) begin
    #1;
    $display("%b %b %b %b %b", CIN, A, B, COUT, S);
end

initial begin
    $dumpfile("tb_test_out.vcd");
    $dumpvars(0, dut);
end

endmodule

07_adder/tb_test_out.vcd
$date
	Tue Dec 28 15:48:32 2021
$end
$version
	Icarus Verilog
$end
$timescale
	1ps
$end
$scope module tb_testbench $end
$scope module dut $end
$var wire 1 ! Cout $end
$var wire 1 " S $end
$var wire 1 # w0 $end
$var wire 1 $ w1 $end
$var wire 1 % w2 $end
$var wire 1 & Cin $end
$var wire 1 ' B $end
$var wire 1 ( A $end
$upscope $end
$upscope $end
$enddefinitions $end
#0
$dumpvars
0(
0'
0&
0%
0$
0#
0"
0!
$end
#100000
1"
1'
#200000
0'
1(
#300000
1!
1#
0"
1'
#400000
0!
0#
1"
0'
0(
1&
#500000
1!
1%
0"
1'
#600000
0%
1$
0'
1(
#700000
1%
1#
1"
1'
